FaBoProximity_VCNL4010
