Metadata-Version: 1.1
Name: FaBoProximity-VCNL4010
Version: 1.0.1
Summary: This is a library for the FaBo Proximity I2C Brick.
Home-page: https://github.com/FaBoPlatform/FaBoProximity-VCNL4010-Python
Author: FaBo
Author-email: info@fabo.io
License: Apache License 2.0
Platform: UNKNOWN
Classifier: Development Status :: 4 - Beta
Classifier: Operating System :: POSIX :: Linux
Classifier: License :: OSI Approved :: Apache Software License
Classifier: Intended Audience :: Developers
Classifier: Programming Language :: Python :: 2.7
Classifier: Topic :: Software Development
Classifier: Topic :: System :: Hardware
